{
    "/Comments_Blog_Post_Wrapper.js": "/Comments_Blog_Post_Wrapper.js?id=69f8b8a8556720c298ae",
    "/assets/js/app.js": "/assets/js/app.js?id=7f02f35dfc147bcb3c6d",
    "/assets/css/app.css": "/assets/css/app.css?id=94f9991304851121ab3d",
    "/AdminLayout-vue.js": "/AdminLayout-vue.js?id=ca310179bf493cc2eca7",
    "/Admin_Blog_Posts_Page.js": "/Admin_Blog_Posts_Page.js?id=d35fda28db6628be03a8",
    "/Admin_Comments_Page.js": "/Admin_Comments_Page.js?id=bf55c4e8232e966f7a60",
    "/Admin_Users_Page.js": "/Admin_Users_Page.js?id=539ec5415aad41b1e3a5",
    "/Blog_Post_Form.js": "/Blog_Post_Form.js?id=120a6eae616f9f65e50f",
    "/Blog_Post_Page.js": "/Blog_Post_Page.js?id=5c89ed3271a53e812d05",
    "/Blog_Posts_Index_Page.js": "/Blog_Posts_Index_Page.js?id=dee324dbd90a7d76f66b",
    "/Comment_Form.js": "/Comment_Form.js?id=05b3a1e18e994448d43a",
    "/Cookie_Consent_Page.js": "/Cookie_Consent_Page.js?id=4e8fa288e9a1cede20ca",
    "/DefaultLayout-vue.js": "/DefaultLayout-vue.js?id=bc0205aab0a761afee45",
    "/Discussion_Page.js": "/Discussion_Page.js?id=b1da11557d8f5008c658",
    "/Forgot_Password_Page.js": "/Forgot_Password_Page.js?id=77fcb3d208d8fec550be",
    "/Home_Page.js": "/Home_Page.js?id=9ef759d5ae997f1eaf91",
    "/Login_Page.js": "/Login_Page.js?id=3590743345782f52aa9b",
    "/Not_Found_Page.js": "/Not_Found_Page.js?id=61518a869f3abd243f46",
    "/Privacy_Policy_Page.js": "/Privacy_Policy_Page.js?id=9c4533f3f31f473cbed1",
    "/Recent_Blog_Posts.js": "/Recent_Blog_Posts.js?id=d6d98246ae85be278dde",
    "/Register_Page.js": "/Register_Page.js?id=21363484db58d56a00e5",
    "/Reset_Password_Page.js": "/Reset_Password_Page.js?id=11619b8e3d8c0f59c8cb",
    "/SidebarLayout-vue.js": "/SidebarLayout-vue.js?id=13601b679a985489aa66",
    "/StackLayout-vue.js": "/StackLayout-vue.js?id=340248345bdf22eb5cd2",
    "/User_Form.js": "/User_Form.js?id=0eb50f08e117c70b6a51"
}
